kolombos/__init__.py
kolombos/__main__.py
kolombos/app.py
kolombos/arghelp.py
kolombos/common.py
kolombos/console.py
kolombos/demo.bin
kolombos/legend.ansi
kolombos/settings.py
kolombos/version.py
kolombos/byteio/__init__.py
kolombos/byteio/common.py
kolombos/byteio/const.py
kolombos/byteio/partial_override.py
kolombos/byteio/reader.py
kolombos/byteio/formatter/__init__.py
kolombos/byteio/formatter/_abstract.py
kolombos/byteio/formatter/binary.py
kolombos/byteio/formatter/factory.py
kolombos/byteio/formatter/text.py
kolombos/byteio/parser/__init__.py
kolombos/byteio/parser/buffer.py
kolombos/byteio/parser/parser.py
kolombos/byteio/segment/__init__.py
kolombos/byteio/segment/buffer.py
kolombos/byteio/segment/chainable.py
kolombos/byteio/segment/printer.py
kolombos/byteio/segment/segment.py
kolombos/byteio/segment/sequence_ref.py
kolombos/byteio/template/__init__.py
kolombos/byteio/template/registry.py
kolombos/byteio/template/template.py
kolombos/byteio/template/template_control.py
kolombos/byteio/template/template_escape.py
kolombos/byteio/template/template_escape_sgr.py
kolombos/byteio/template/template_newline.py
kolombos/byteio/template/template_printable.py
kolombos/byteio/template/template_utf8.py
kolombos/runner/__init__.py
kolombos/runner/_abstract.py
kolombos/runner/byteio.py
kolombos/runner/demo.py
kolombos/runner/factory.py
kolombos/runner/legend.py
kolombos/runner/version.py
pytermor/__init__.py
pytermor/__main__.py
pytermor/_version.py
pytermor/ansi.py
pytermor/color.py
pytermor/common.py
pytermor/render.py
pytermor/util/__init__.py
pytermor/util/auto_float.py
pytermor/util/prefixed_unit.py
pytermor/util/stdlib_ext.py
pytermor/util/string_filter.py
pytermor/util/time_delta.py
kolombos-1.5.4.dist-info/LICENSE
kolombos-1.5.4.dist-info/METADATA
kolombos-1.5.4.dist-info/WHEEL
kolombos-1.5.4.dist-info/entry_points.txt
kolombos-1.5.4.dist-info/top_level.txt
kolombos-1.5.4.dist-info/RECORD
