Metadata-Version: 2.1
Name: kolombos
Version: 1.5.4
Summary: CLI control characters and escape sequences viewer/visualizer
Home-page: https://github.com/es7s/kolombos
Author: Aleksandr Shavykin
Author-email: 0.delameter@gmail.com
Classifier: Environment :: Console
Classifier: Intended Audience :: Developers
Classifier: Programming Language :: Python :: 3
Classifier: License :: OSI Approved :: MIT License
Classifier: Operating System :: OS Independent
Classifier: Topic :: Terminals
Requires-Python: >=3.7
License-File: LICENSE
